esmerald_sessions/__init__.py
esmerald_sessions/backends.py
esmerald_sessions/config.py
esmerald_sessions/datastructures.py
esmerald_sessions/enums.py
esmerald_sessions/exceptions.py
esmerald_sessions/middleware.py
esmerald_sessions/protocols.py
esmerald_sessions/py.typed
esmerald_sessions/types.py
esmerald_sessions-0.3.0.dist-info/METADATA
esmerald_sessions-0.3.0.dist-info/WHEEL
esmerald_sessions-0.3.0.dist-info/licenses/LICENSE
esmerald_sessions-0.3.0.dist-info/RECORD
